ochrus/__init__.py
ochrus/blackbox.py
ochrus/config.py
ochrus/http_session.py
ochrus/ip_object.py
ochrus/logger.py
ochrus/setup.py
ochrus/ssh.py
ochrus/timestamp.py
ochrus/txtfile.py
ochrus-0.0.61.dist-info/LICENCE
ochrus-0.0.61.dist-info/METADATA
ochrus-0.0.61.dist-info/WHEEL
ochrus-0.0.61.dist-info/top_level.txt
ochrus-0.0.61.dist-info/RECORD
