Metadata-Version: 2.1
Name: ochrus
Version: 0.0.61
Summary: Ochrus functional test automation infrastructure
Home-page: https://github.com/ochrus/ochrus
Author: Roni Eliezer
Author-email: roniezr@gmail.com
License: MIT
Download-URL: https://github.com/ochrus/ochrus-0.0.61.tar.gz
Keywords: functional,testing,automation,infrastructure
Platform: UNKNOWN
Requires-Dist: paramiko
Requires-Dist: requests
